logeer.py
logeer-0.0.2.dist-info/METADATA
logeer-0.0.2.dist-info/WHEEL
logeer-0.0.2.dist-info/entry_points.txt
logeer-0.0.2.dist-info/top_level.txt
logeer-0.0.2.dist-info/RECORD
